quickargs/__init__.py
quickargs/quickargs.py
quickargs/tests.py
quickargs-0.1.dist-info/DESCRIPTION.rst
quickargs-0.1.dist-info/METADATA
quickargs-0.1.dist-info/RECORD
quickargs-0.1.dist-info/WHEEL
quickargs-0.1.dist-info/metadata.json
quickargs-0.1.dist-info/top_level.txt
