Metadata-Version: 2.0
Name: quickargs
Version: 0.1
Summary: YAML config file -> command line interface
Home-page: https://github.com/krasch/quickargs
Author: krasch
Author-email: code@krasch.io
License: MIT
Platform: UNKNOWN
Classifier: Development Status :: 3 - Alpha
Classifier: Intended Audience :: Developers
Classifier: Topic :: Software Development
Classifier: License :: OSI Approved :: MIT License
Classifier: Programming Language :: Python :: 2
Classifier: Programming Language :: Python :: 3
Requires-Dist: pyyaml (>=3.10)
